flipnote/__init__.py
flipnote/kwz.py
flipnote/ppm.py
flipnote/schema.py
flipnote-0.1.3.dist-info/LICENSE
flipnote-0.1.3.dist-info/METADATA
flipnote-0.1.3.dist-info/WHEEL
flipnote-0.1.3.dist-info/top_level.txt
flipnote-0.1.3.dist-info/RECORD
