Metadata-Version: 2.1
Name: flipnote
Version: 0.1.3
Summary: A Python library for Flipnote Studio (3D) files
Home-page: https://github.com/meemo/flipnote.py
Author: Meemo
Author-email: meemo4556@gmail.com
License: MIT
Project-URL: Bug Tracker, https://github.com/meemo/flipnote.py/issues
Platform: UNKNOWN
Classifier: Programming Language :: Python :: 3
Classifier: License :: OSI Approved :: MIT License
Classifier: Operating System :: OS Independent
Requires-Python: >=3.7
License-File: LICENSE
Requires-Dist: numpy
